log_suraj-0.1.dist-info/DESCRIPTION.rst
log_suraj-0.1.dist-info/METADATA
log_suraj-0.1.dist-info/RECORD
log_suraj-0.1.dist-info/WHEEL
log_suraj-0.1.dist-info/metadata.json
log_suraj-0.1.dist-info/top_level.txt
logger_suraj/__init__.py
logger_suraj/log.py
